master_strange_mol_rep/__init__.py
master_strange_mol_rep/mol_rep.py
master_strange_mol_rep-0.0.1.dist-info/METADATA
master_strange_mol_rep-0.0.1.dist-info/WHEEL
master_strange_mol_rep-0.0.1.dist-info/licenses/LICENSE
master_strange_mol_rep-0.0.1.dist-info/RECORD
