Metadata-Version: 2.1
Name: master_strange_mol_rep
Version: 0.0.1
Summary: Stiv Llenga (Master Strange) created this simple package to assist master students and other researchers who are working on generating molecular representations and manipulating arrays in various forms.
Author-email: Stiv Llenga <stiv.llenga@h-its.org>
License: MIT License
Classifier: License :: OSI Approved :: MIT License
Classifier: Operating System :: OS Independent
Classifier: Programming Language :: Python :: 3
Requires-Python: >=3.7
